growatt/__init__.py
growatt/__main__.py
growatt-0.0.4.dist-info/LICENSE
growatt-0.0.4.dist-info/METADATA
growatt-0.0.4.dist-info/WHEEL
growatt-0.0.4.dist-info/top_level.txt
growatt-0.0.4.dist-info/RECORD
