Metadata-Version: 2.1
Name: growatt
Version: 0.0.4
Summary: Growatt API for photovoltaic statistics
Home-page: https://github.com/Sjord/growatt_api_client
Author: Sjoerd Langkemper
License: OSI Approved :: MIT License
Platform: UNKNOWN
Classifier: Development Status :: 4 - Beta
Classifier: License :: OSI Approved :: MIT License
Classifier: Programming Language :: Python
License-File: LICENSE
Requires-Dist: requests
